bloop/__init__.py
bloop/actions.py
bloop/conditions.py
bloop/engine.py
bloop/exceptions.py
bloop/models.py
bloop/search.py
bloop/session.py
bloop/signals.py
bloop/transactions.py
bloop/types.py
bloop/util.py
bloop/ext/__init__.py
bloop/ext/arrow.py
bloop/ext/delorean.py
bloop/ext/pendulum.py
bloop/stream/__init__.py
bloop/stream/buffer.py
bloop/stream/coordinator.py
bloop/stream/shard.py
bloop/stream/stream.py
tests/helpers/__init__.py
tests/helpers/models.py
tests/helpers/utils.py
tests/integ/__init__.py
tests/integ/conftest.py
tests/integ/models.py
tests/integ/test_basic.py
tests/integ/test_inheritance.py
tests/integ/test_queries.py
tests/unit/__init__.py
tests/unit/conftest.py
tests/unit/test_actions.py
tests/unit/test_conditions.py
tests/unit/test_engine.py
tests/unit/test_models.py
tests/unit/test_search.py
tests/unit/test_session.py
tests/unit/test_transactions.py
tests/unit/test_types.py
tests/unit/test_util.py
tests/unit/test_ext/__init__.py
tests/unit/test_ext/test_arrow.py
tests/unit/test_ext/test_delorean.py
tests/unit/test_ext/test_pendulum.py
tests/unit/test_stream/__init__.py
tests/unit/test_stream/conftest.py
tests/unit/test_stream/test_buffer.py
tests/unit/test_stream/test_coordinator.py
tests/unit/test_stream/test_shard.py
tests/unit/test_stream/test_stream.py
bloop-3.1.1.dist-info/LICENSE
bloop-3.1.1.dist-info/METADATA
bloop-3.1.1.dist-info/WHEEL
bloop-3.1.1.dist-info/top_level.txt
bloop-3.1.1.dist-info/RECORD
