Metadata-Version: 2.1
Name: bloop
Version: 3.1.1
Summary: ORM for DynamoDB
Home-page: https://github.com/numberoverzero/bloop
Author: Joe Cross
Author-email: joe.mcross@gmail.com
License: MIT
Keywords: aws dynamo dynamodb dynamodbstreams orm
Platform: any
Classifier: Development Status :: 5 - Production/Stable
Classifier: Intended Audience :: Developers
Classifier: License :: OSI Approved :: MIT License
Classifier: Operating System :: OS Independent
Classifier: Programming Language :: Python
Classifier: Programming Language :: Python :: 3
Classifier: Programming Language :: Python :: 3.6
Classifier: Topic :: Software Development :: Libraries
License-File: LICENSE
Requires-Dist: blinker ==1.8.2
Requires-Dist: boto3 ==1.34.131
